ebosc/BOSC.py
ebosc/__init__.py
ebosc/eBOSC.py
ebosc/eBOSC_wrapper.py
ebosc/helpers.py
ebosc/version.py
ebosc-0.10.dev0.dist-info/LICENSE
ebosc-0.10.dev0.dist-info/METADATA
ebosc-0.10.dev0.dist-info/WHEEL
ebosc-0.10.dev0.dist-info/top_level.txt
ebosc-0.10.dev0.dist-info/RECORD
