Metadata-Version: 2.1
Name: ebosc
Version: 0.10.dev0
Summary: extended Better Oscillation Detection, implemented in python3
Home-page: https://github.com/jkosciessa/eBOSC_py/
Maintainer: Julian Kosciessa
Maintainer-email: kosciessa@mpib-berlin.mpg.de
License: GPL
Project-URL: Issue Tracker, https://github.com/jkosciessa/eBOSC_py/issues
Keywords: neural rhythms,electrophysiology,EEG,neuroscience
Platform: UNKNOWN
Classifier: Development Status :: 4 - Beta
Classifier: Intended Audience :: Science/Research
Classifier: License :: OSI Approved :: GNU General Public License v3 or later (GPLv3+)
Classifier: Operating System :: Unix
Classifier: Operating System :: POSIX
Classifier: Operating System :: Microsoft :: Windows
Classifier: Natural Language :: English
Classifier: Programming Language :: Python :: 3
Classifier: Topic :: Scientific/Engineering
Requires-Python: >=3.6
License-File: LICENSE
Requires-Dist: numpy
Requires-Dist: scipy
Requires-Dist: pandas
Requires-Dist: statsmodels
Requires-Dist: matplotlib
